textron_logging/__init__.py
textron_logging/textron_logger.py
textron_logging-1.0.6.dist-info/METADATA
textron_logging-1.0.6.dist-info/WHEEL
textron_logging-1.0.6.dist-info/top_level.txt
textron_logging-1.0.6.dist-info/RECORD
