Metadata-Version: 2.4
Name: textron-logging
Version: 1.0.6
Summary: Minimal uniform logging for Textron apps (console + optional Azure Monitor)
Author: Your Name
Requires-Python: >=3.8
Provides-Extra: azure
Requires-Dist: opentelemetry-sdk>=1.24.0; extra == "azure"
Requires-Dist: azure-monitor-opentelemetry-exporter>=1.0.0; extra == "azure"
Dynamic: author
Dynamic: provides-extra
Dynamic: requires-python
Dynamic: summary
